package com.p046a.p049b.p050a.p052b;

import android.support.v7.appcompat.C0327R;
import com.gmail.heagoo.p084a.p089c.C1067a;

/* JADX INFO: renamed from: com.a.b.a.b.g */
/* JADX INFO: loaded from: classes.dex */
public final class C0551g {

    /* JADX INFO: renamed from: a */
    private static final int[] f882a = new int[256];

    /* JADX INFO: renamed from: b */
    private static final String[] f883b = new String[256];

    static {
        int i;
        int length = "00 - nop;01 - aconst_null;02 - iconst_m1;03 - iconst_0;04 - iconst_1;05 - iconst_2;06 - iconst_3;07 - iconst_4;08 - iconst_5;09 - lconst_0;0a - lconst_1;0b - fconst_0;0c - fconst_1;0d - fconst_2;0e - dconst_0;0f - dconst_1;10 y bipush;11 S sipush;12 L:IFcs ldc;13 p:IFcs ldc_w;14 p:DJ ldc2_w;15 l iload;16 m lload;17 l fload;18 m dload;19 l aload;1a 0 iload_0;1b 1 iload_1;1c 2 iload_2;1d 3 iload_3;1e 1 lload_0;1f 2 lload_1;20 3 lload_2;21 4 lload_3;22 0 fload_0;23 1 fload_1;24 2 fload_2;25 3 fload_3;26 1 dload_0;27 2 dload_1;28 3 dload_2;29 4 dload_3;2a 0 aload_0;2b 1 aload_1;2c 2 aload_2;2d 3 aload_3;2e - iaload;2f - laload;30 - faload;31 - daload;32 - aaload;33 - baload;34 - caload;35 - saload;36 - istore;37 - lstore;38 - fstore;39 - dstore;3a - astore;3b 0 istore_0;3c 1 istore_1;3d 2 istore_2;3e 3 istore_3;3f 1 lstore_0;40 2 lstore_1;41 3 lstore_2;42 4 lstore_3;43 0 fstore_0;44 1 fstore_1;45 2 fstore_2;46 3 fstore_3;47 1 dstore_0;48 2 dstore_1;49 3 dstore_2;4a 4 dstore_3;4b 0 astore_0;4c 1 astore_1;4d 2 astore_2;4e 3 astore_3;4f - iastore;50 - lastore;51 - fastore;52 - dastore;53 - aastore;54 - bastore;55 - castore;56 - sastore;57 - pop;58 - pop2;59 - dup;5a - dup_x1;5b - dup_x2;5c - dup2;5d - dup2_x1;5e - dup2_x2;5f - swap;60 - iadd;61 - ladd;62 - fadd;63 - dadd;64 - isub;65 - lsub;66 - fsub;67 - dsub;68 - imul;69 - lmul;6a - fmul;6b - dmul;6c - idiv;6d - ldiv;6e - fdiv;6f - ddiv;70 - irem;71 - lrem;72 - frem;73 - drem;74 - ineg;75 - lneg;76 - fneg;77 - dneg;78 - ishl;79 - lshl;7a - ishr;7b - lshr;7c - iushr;7d - lushr;7e - iand;7f - land;80 - ior;81 - lor;82 - ixor;83 - lxor;84 l iinc;85 - i2l;86 - i2f;87 - i2d;88 - l2i;89 - l2f;8a - l2d;8b - f2i;8c - f2l;8d - f2d;8e - d2i;8f - d2l;90 - d2f;91 - i2b;92 - i2c;93 - i2s;94 - lcmp;95 - fcmpl;96 - fcmpg;97 - dcmpl;98 - dcmpg;99 b ifeq;9a b ifne;9b b iflt;9c b ifge;9d b ifgt;9e b ifle;9f b if_icmpeq;a0 b if_icmpne;a1 b if_icmplt;a2 b if_icmpge;a3 b if_icmpgt;a4 b if_icmple;a5 b if_acmpeq;a6 b if_acmpne;a7 b goto;a8 b jsr;a9 l ret;aa T tableswitch;ab U lookupswitch;ac - ireturn;ad - lreturn;ae - freturn;af - dreturn;b0 - areturn;b1 - return;b2 p:f getstatic;b3 p:f putstatic;b4 p:f getfield;b5 p:f putfield;b6 p:m invokevirtual;b7 p:m invokespecial;b8 p:m invokestatic;b9 I:i invokeinterface;bb p:c new;bc y newarray;bd p:c anewarray;be - arraylength;bf - athrow;c0 p:c checkcast;c1 p:c instanceof;c2 - monitorenter;c3 - monitorexit;c4 W wide;c5 M:c multianewarray;c6 b ifnull;c7 b ifnonnull;c8 c goto_w;c9 c jsr_w;".length();
        int i2 = 0;
        while (i2 < length) {
            int iDigit = Character.digit("00 - nop;01 - aconst_null;02 - iconst_m1;03 - iconst_0;04 - iconst_1;05 - iconst_2;06 - iconst_3;07 - iconst_4;08 - iconst_5;09 - lconst_0;0a - lconst_1;0b - fconst_0;0c - fconst_1;0d - fconst_2;0e - dconst_0;0f - dconst_1;10 y bipush;11 S sipush;12 L:IFcs ldc;13 p:IFcs ldc_w;14 p:DJ ldc2_w;15 l iload;16 m lload;17 l fload;18 m dload;19 l aload;1a 0 iload_0;1b 1 iload_1;1c 2 iload_2;1d 3 iload_3;1e 1 lload_0;1f 2 lload_1;20 3 lload_2;21 4 lload_3;22 0 fload_0;23 1 fload_1;24 2 fload_2;25 3 fload_3;26 1 dload_0;27 2 dload_1;28 3 dload_2;29 4 dload_3;2a 0 aload_0;2b 1 aload_1;2c 2 aload_2;2d 3 aload_3;2e - iaload;2f - laload;30 - faload;31 - daload;32 - aaload;33 - baload;34 - caload;35 - saload;36 - istore;37 - lstore;38 - fstore;39 - dstore;3a - astore;3b 0 istore_0;3c 1 istore_1;3d 2 istore_2;3e 3 istore_3;3f 1 lstore_0;40 2 lstore_1;41 3 lstore_2;42 4 lstore_3;43 0 fstore_0;44 1 fstore_1;45 2 fstore_2;46 3 fstore_3;47 1 dstore_0;48 2 dstore_1;49 3 dstore_2;4a 4 dstore_3;4b 0 astore_0;4c 1 astore_1;4d 2 astore_2;4e 3 astore_3;4f - iastore;50 - lastore;51 - fastore;52 - dastore;53 - aastore;54 - bastore;55 - castore;56 - sastore;57 - pop;58 - pop2;59 - dup;5a - dup_x1;5b - dup_x2;5c - dup2;5d - dup2_x1;5e - dup2_x2;5f - swap;60 - iadd;61 - ladd;62 - fadd;63 - dadd;64 - isub;65 - lsub;66 - fsub;67 - dsub;68 - imul;69 - lmul;6a - fmul;6b - dmul;6c - idiv;6d - ldiv;6e - fdiv;6f - ddiv;70 - irem;71 - lrem;72 - frem;73 - drem;74 - ineg;75 - lneg;76 - fneg;77 - dneg;78 - ishl;79 - lshl;7a - ishr;7b - lshr;7c - iushr;7d - lushr;7e - iand;7f - land;80 - ior;81 - lor;82 - ixor;83 - lxor;84 l iinc;85 - i2l;86 - i2f;87 - i2d;88 - l2i;89 - l2f;8a - l2d;8b - f2i;8c - f2l;8d - f2d;8e - d2i;8f - d2l;90 - d2f;91 - i2b;92 - i2c;93 - i2s;94 - lcmp;95 - fcmpl;96 - fcmpg;97 - dcmpl;98 - dcmpg;99 b ifeq;9a b ifne;9b b iflt;9c b ifge;9d b ifgt;9e b ifle;9f b if_icmpeq;a0 b if_icmpne;a1 b if_icmplt;a2 b if_icmpge;a3 b if_icmpgt;a4 b if_icmple;a5 b if_acmpeq;a6 b if_acmpne;a7 b goto;a8 b jsr;a9 l ret;aa T tableswitch;ab U lookupswitch;ac - ireturn;ad - lreturn;ae - freturn;af - dreturn;b0 - areturn;b1 - return;b2 p:f getstatic;b3 p:f putstatic;b4 p:f getfield;b5 p:f putfield;b6 p:m invokevirtual;b7 p:m invokespecial;b8 p:m invokestatic;b9 I:i invokeinterface;bb p:c new;bc y newarray;bd p:c anewarray;be - arraylength;bf - athrow;c0 p:c checkcast;c1 p:c instanceof;c2 - monitorenter;c3 - monitorexit;c4 W wide;c5 M:c multianewarray;c6 b ifnull;c7 b ifnonnull;c8 c goto_w;c9 c jsr_w;".charAt(i2 + 1), 16) | (Character.digit("00 - nop;01 - aconst_null;02 - iconst_m1;03 - iconst_0;04 - iconst_1;05 - iconst_2;06 - iconst_3;07 - iconst_4;08 - iconst_5;09 - lconst_0;0a - lconst_1;0b - fconst_0;0c - fconst_1;0d - fconst_2;0e - dconst_0;0f - dconst_1;10 y bipush;11 S sipush;12 L:IFcs ldc;13 p:IFcs ldc_w;14 p:DJ ldc2_w;15 l iload;16 m lload;17 l fload;18 m dload;19 l aload;1a 0 iload_0;1b 1 iload_1;1c 2 iload_2;1d 3 iload_3;1e 1 lload_0;1f 2 lload_1;20 3 lload_2;21 4 lload_3;22 0 fload_0;23 1 fload_1;24 2 fload_2;25 3 fload_3;26 1 dload_0;27 2 dload_1;28 3 dload_2;29 4 dload_3;2a 0 aload_0;2b 1 aload_1;2c 2 aload_2;2d 3 aload_3;2e - iaload;2f - laload;30 - faload;31 - daload;32 - aaload;33 - baload;34 - caload;35 - saload;36 - istore;37 - lstore;38 - fstore;39 - dstore;3a - astore;3b 0 istore_0;3c 1 istore_1;3d 2 istore_2;3e 3 istore_3;3f 1 lstore_0;40 2 lstore_1;41 3 lstore_2;42 4 lstore_3;43 0 fstore_0;44 1 fstore_1;45 2 fstore_2;46 3 fstore_3;47 1 dstore_0;48 2 dstore_1;49 3 dstore_2;4a 4 dstore_3;4b 0 astore_0;4c 1 astore_1;4d 2 astore_2;4e 3 astore_3;4f - iastore;50 - lastore;51 - fastore;52 - dastore;53 - aastore;54 - bastore;55 - castore;56 - sastore;57 - pop;58 - pop2;59 - dup;5a - dup_x1;5b - dup_x2;5c - dup2;5d - dup2_x1;5e - dup2_x2;5f - swap;60 - iadd;61 - ladd;62 - fadd;63 - dadd;64 - isub;65 - lsub;66 - fsub;67 - dsub;68 - imul;69 - lmul;6a - fmul;6b - dmul;6c - idiv;6d - ldiv;6e - fdiv;6f - ddiv;70 - irem;71 - lrem;72 - frem;73 - drem;74 - ineg;75 - lneg;76 - fneg;77 - dneg;78 - ishl;79 - lshl;7a - ishr;7b - lshr;7c - iushr;7d - lushr;7e - iand;7f - land;80 - ior;81 - lor;82 - ixor;83 - lxor;84 l iinc;85 - i2l;86 - i2f;87 - i2d;88 - l2i;89 - l2f;8a - l2d;8b - f2i;8c - f2l;8d - f2d;8e - d2i;8f - d2l;90 - d2f;91 - i2b;92 - i2c;93 - i2s;94 - lcmp;95 - fcmpl;96 - fcmpg;97 - dcmpl;98 - dcmpg;99 b ifeq;9a b ifne;9b b iflt;9c b ifge;9d b ifgt;9e b ifle;9f b if_icmpeq;a0 b if_icmpne;a1 b if_icmplt;a2 b if_icmpge;a3 b if_icmpgt;a4 b if_icmple;a5 b if_acmpeq;a6 b if_acmpne;a7 b goto;a8 b jsr;a9 l ret;aa T tableswitch;ab U lookupswitch;ac - ireturn;ad - lreturn;ae - freturn;af - dreturn;b0 - areturn;b1 - return;b2 p:f getstatic;b3 p:f putstatic;b4 p:f getfield;b5 p:f putfield;b6 p:m invokevirtual;b7 p:m invokespecial;b8 p:m invokestatic;b9 I:i invokeinterface;bb p:c new;bc y newarray;bd p:c anewarray;be - arraylength;bf - athrow;c0 p:c checkcast;c1 p:c instanceof;c2 - monitorenter;c3 - monitorexit;c4 W wide;c5 M:c multianewarray;c6 b ifnull;c7 b ifnonnull;c8 c goto_w;c9 c jsr_w;".charAt(i2), 16) << 4);
            switch ("00 - nop;01 - aconst_null;02 - iconst_m1;03 - iconst_0;04 - iconst_1;05 - iconst_2;06 - iconst_3;07 - iconst_4;08 - iconst_5;09 - lconst_0;0a - lconst_1;0b - fconst_0;0c - fconst_1;0d - fconst_2;0e - dconst_0;0f - dconst_1;10 y bipush;11 S sipush;12 L:IFcs ldc;13 p:IFcs ldc_w;14 p:DJ ldc2_w;15 l iload;16 m lload;17 l fload;18 m dload;19 l aload;1a 0 iload_0;1b 1 iload_1;1c 2 iload_2;1d 3 iload_3;1e 1 lload_0;1f 2 lload_1;20 3 lload_2;21 4 lload_3;22 0 fload_0;23 1 fload_1;24 2 fload_2;25 3 fload_3;26 1 dload_0;27 2 dload_1;28 3 dload_2;29 4 dload_3;2a 0 aload_0;2b 1 aload_1;2c 2 aload_2;2d 3 aload_3;2e - iaload;2f - laload;30 - faload;31 - daload;32 - aaload;33 - baload;34 - caload;35 - saload;36 - istore;37 - lstore;38 - fstore;39 - dstore;3a - astore;3b 0 istore_0;3c 1 istore_1;3d 2 istore_2;3e 3 istore_3;3f 1 lstore_0;40 2 lstore_1;41 3 lstore_2;42 4 lstore_3;43 0 fstore_0;44 1 fstore_1;45 2 fstore_2;46 3 fstore_3;47 1 dstore_0;48 2 dstore_1;49 3 dstore_2;4a 4 dstore_3;4b 0 astore_0;4c 1 astore_1;4d 2 astore_2;4e 3 astore_3;4f - iastore;50 - lastore;51 - fastore;52 - dastore;53 - aastore;54 - bastore;55 - castore;56 - sastore;57 - pop;58 - pop2;59 - dup;5a - dup_x1;5b - dup_x2;5c - dup2;5d - dup2_x1;5e - dup2_x2;5f - swap;60 - iadd;61 - ladd;62 - fadd;63 - dadd;64 - isub;65 - lsub;66 - fsub;67 - dsub;68 - imul;69 - lmul;6a - fmul;6b - dmul;6c - idiv;6d - ldiv;6e - fdiv;6f - ddiv;70 - irem;71 - lrem;72 - frem;73 - drem;74 - ineg;75 - lneg;76 - fneg;77 - dneg;78 - ishl;79 - lshl;7a - ishr;7b - lshr;7c - iushr;7d - lushr;7e - iand;7f - land;80 - ior;81 - lor;82 - ixor;83 - lxor;84 l iinc;85 - i2l;86 - i2f;87 - i2d;88 - l2i;89 - l2f;8a - l2d;8b - f2i;8c - f2l;8d - f2d;8e - d2i;8f - d2l;90 - d2f;91 - i2b;92 - i2c;93 - i2s;94 - lcmp;95 - fcmpl;96 - fcmpg;97 - dcmpl;98 - dcmpg;99 b ifeq;9a b ifne;9b b iflt;9c b ifge;9d b ifgt;9e b ifle;9f b if_icmpeq;a0 b if_icmpne;a1 b if_icmplt;a2 b if_icmpge;a3 b if_icmpgt;a4 b if_icmple;a5 b if_acmpeq;a6 b if_acmpne;a7 b goto;a8 b jsr;a9 l ret;aa T tableswitch;ab U lookupswitch;ac - ireturn;ad - lreturn;ae - freturn;af - dreturn;b0 - areturn;b1 - return;b2 p:f getstatic;b3 p:f putstatic;b4 p:f getfield;b5 p:f putfield;b6 p:m invokevirtual;b7 p:m invokespecial;b8 p:m invokestatic;b9 I:i invokeinterface;bb p:c new;bc y newarray;bd p:c anewarray;be - arraylength;bf - athrow;c0 p:c checkcast;c1 p:c instanceof;c2 - monitorenter;c3 - monitorexit;c4 W wide;c5 M:c multianewarray;c6 b ifnull;c7 b ifnonnull;c8 c goto_w;c9 c jsr_w;".charAt(i2 + 3)) {
                case '-':
                    i = 1;
                    break;
                case C0327R.styleable.AppCompatTheme_dropdownListPreferredItemHeight /* 48 */:
                    i = 2;
                    break;
                case C0327R.styleable.AppCompatTheme_spinnerDropDownItemStyle /* 49 */:
                    i = 3;
                    break;
                case '2':
                    i = 4;
                    break;
                case C0327R.styleable.AppCompatTheme_actionButtonStyle /* 51 */:
                    i = 5;
                    break;
                case C0327R.styleable.AppCompatTheme_buttonBarStyle /* 52 */:
                    i = 6;
                    break;
                case C0327R.styleable.AppCompatTheme_listPreferredItemHeightLarge /* 73 */:
                    i = 13;
                    break;
                case C0327R.styleable.AppCompatTheme_dropDownListViewStyle /* 76 */:
                    i = 14;
                    break;
                case C0327R.styleable.AppCompatTheme_listPopupWindowStyle /* 77 */:
                    i = 18;
                    break;
                case C0327R.styleable.AppCompatTheme_panelMenuListTheme /* 83 */:
                    i = 15;
                    break;
                case C0327R.styleable.AppCompatTheme_listChoiceBackgroundIndicator /* 84 */:
                    i = 16;
                    break;
                case C0327R.styleable.AppCompatTheme_colorPrimary /* 85 */:
                    i = 17;
                    break;
                case C0327R.styleable.AppCompatTheme_colorAccent /* 87 */:
                    i = 19;
                    break;
                case C0327R.styleable.AppCompatTheme_alertDialogTheme /* 98 */:
                    i = 7;
                    break;
                case C0327R.styleable.AppCompatTheme_textColorAlertDialogListItem /* 99 */:
                    i = 8;
                    break;
                case 'l':
                    i = 10;
                    break;
                case 'm':
                    i = 11;
                    break;
                case C0327R.styleable.AppCompatTheme_ratingBarStyleSmall /* 112 */:
                    i = 9;
                    break;
                case 'y':
                    i = 12;
                    break;
                default:
                    i = 0;
                    break;
            }
            int i3 = i2 + 5;
            if ("00 - nop;01 - aconst_null;02 - iconst_m1;03 - iconst_0;04 - iconst_1;05 - iconst_2;06 - iconst_3;07 - iconst_4;08 - iconst_5;09 - lconst_0;0a - lconst_1;0b - fconst_0;0c - fconst_1;0d - fconst_2;0e - dconst_0;0f - dconst_1;10 y bipush;11 S sipush;12 L:IFcs ldc;13 p:IFcs ldc_w;14 p:DJ ldc2_w;15 l iload;16 m lload;17 l fload;18 m dload;19 l aload;1a 0 iload_0;1b 1 iload_1;1c 2 iload_2;1d 3 iload_3;1e 1 lload_0;1f 2 lload_1;20 3 lload_2;21 4 lload_3;22 0 fload_0;23 1 fload_1;24 2 fload_2;25 3 fload_3;26 1 dload_0;27 2 dload_1;28 3 dload_2;29 4 dload_3;2a 0 aload_0;2b 1 aload_1;2c 2 aload_2;2d 3 aload_3;2e - iaload;2f - laload;30 - faload;31 - daload;32 - aaload;33 - baload;34 - caload;35 - saload;36 - istore;37 - lstore;38 - fstore;39 - dstore;3a - astore;3b 0 istore_0;3c 1 istore_1;3d 2 istore_2;3e 3 istore_3;3f 1 lstore_0;40 2 lstore_1;41 3 lstore_2;42 4 lstore_3;43 0 fstore_0;44 1 fstore_1;45 2 fstore_2;46 3 fstore_3;47 1 dstore_0;48 2 dstore_1;49 3 dstore_2;4a 4 dstore_3;4b 0 astore_0;4c 1 astore_1;4d 2 astore_2;4e 3 astore_3;4f - iastore;50 - lastore;51 - fastore;52 - dastore;53 - aastore;54 - bastore;55 - castore;56 - sastore;57 - pop;58 - pop2;59 - dup;5a - dup_x1;5b - dup_x2;5c - dup2;5d - dup2_x1;5e - dup2_x2;5f - swap;60 - iadd;61 - ladd;62 - fadd;63 - dadd;64 - isub;65 - lsub;66 - fsub;67 - dsub;68 - imul;69 - lmul;6a - fmul;6b - dmul;6c - idiv;6d - ldiv;6e - fdiv;6f - ddiv;70 - irem;71 - lrem;72 - frem;73 - drem;74 - ineg;75 - lneg;76 - fneg;77 - dneg;78 - ishl;79 - lshl;7a - ishr;7b - lshr;7c - iushr;7d - lushr;7e - iand;7f - land;80 - ior;81 - lor;82 - ixor;83 - lxor;84 l iinc;85 - i2l;86 - i2f;87 - i2d;88 - l2i;89 - l2f;8a - l2d;8b - f2i;8c - f2l;8d - f2d;8e - d2i;8f - d2l;90 - d2f;91 - i2b;92 - i2c;93 - i2s;94 - lcmp;95 - fcmpl;96 - fcmpg;97 - dcmpl;98 - dcmpg;99 b ifeq;9a b ifne;9b b iflt;9c b ifge;9d b ifgt;9e b ifle;9f b if_icmpeq;a0 b if_icmpne;a1 b if_icmplt;a2 b if_icmpge;a3 b if_icmpgt;a4 b if_icmple;a5 b if_acmpeq;a6 b if_acmpne;a7 b goto;a8 b jsr;a9 l ret;aa T tableswitch;ab U lookupswitch;ac - ireturn;ad - lreturn;ae - freturn;af - dreturn;b0 - areturn;b1 - return;b2 p:f getstatic;b3 p:f putstatic;b4 p:f getfield;b5 p:f putfield;b6 p:m invokevirtual;b7 p:m invokespecial;b8 p:m invokestatic;b9 I:i invokeinterface;bb p:c new;bc y newarray;bd p:c anewarray;be - arraylength;bf - athrow;c0 p:c checkcast;c1 p:c instanceof;c2 - monitorenter;c3 - monitorexit;c4 W wide;c5 M:c multianewarray;c6 b ifnull;c7 b ifnonnull;c8 c goto_w;c9 c jsr_w;".charAt(i3 - 1) == ':') {
                while (true) {
                    switch ("00 - nop;01 - aconst_null;02 - iconst_m1;03 - iconst_0;04 - iconst_1;05 - iconst_2;06 - iconst_3;07 - iconst_4;08 - iconst_5;09 - lconst_0;0a - lconst_1;0b - fconst_0;0c - fconst_1;0d - fconst_2;0e - dconst_0;0f - dconst_1;10 y bipush;11 S sipush;12 L:IFcs ldc;13 p:IFcs ldc_w;14 p:DJ ldc2_w;15 l iload;16 m lload;17 l fload;18 m dload;19 l aload;1a 0 iload_0;1b 1 iload_1;1c 2 iload_2;1d 3 iload_3;1e 1 lload_0;1f 2 lload_1;20 3 lload_2;21 4 lload_3;22 0 fload_0;23 1 fload_1;24 2 fload_2;25 3 fload_3;26 1 dload_0;27 2 dload_1;28 3 dload_2;29 4 dload_3;2a 0 aload_0;2b 1 aload_1;2c 2 aload_2;2d 3 aload_3;2e - iaload;2f - laload;30 - faload;31 - daload;32 - aaload;33 - baload;34 - caload;35 - saload;36 - istore;37 - lstore;38 - fstore;39 - dstore;3a - astore;3b 0 istore_0;3c 1 istore_1;3d 2 istore_2;3e 3 istore_3;3f 1 lstore_0;40 2 lstore_1;41 3 lstore_2;42 4 lstore_3;43 0 fstore_0;44 1 fstore_1;45 2 fstore_2;46 3 fstore_3;47 1 dstore_0;48 2 dstore_1;49 3 dstore_2;4a 4 dstore_3;4b 0 astore_0;4c 1 astore_1;4d 2 astore_2;4e 3 astore_3;4f - iastore;50 - lastore;51 - fastore;52 - dastore;53 - aastore;54 - bastore;55 - castore;56 - sastore;57 - pop;58 - pop2;59 - dup;5a - dup_x1;5b - dup_x2;5c - dup2;5d - dup2_x1;5e - dup2_x2;5f - swap;60 - iadd;61 - ladd;62 - fadd;63 - dadd;64 - isub;65 - lsub;66 - fsub;67 - dsub;68 - imul;69 - lmul;6a - fmul;6b - dmul;6c - idiv;6d - ldiv;6e - fdiv;6f - ddiv;70 - irem;71 - lrem;72 - frem;73 - drem;74 - ineg;75 - lneg;76 - fneg;77 - dneg;78 - ishl;79 - lshl;7a - ishr;7b - lshr;7c - iushr;7d - lushr;7e - iand;7f - land;80 - ior;81 - lor;82 - ixor;83 - lxor;84 l iinc;85 - i2l;86 - i2f;87 - i2d;88 - l2i;89 - l2f;8a - l2d;8b - f2i;8c - f2l;8d - f2d;8e - d2i;8f - d2l;90 - d2f;91 - i2b;92 - i2c;93 - i2s;94 - lcmp;95 - fcmpl;96 - fcmpg;97 - dcmpl;98 - dcmpg;99 b ifeq;9a b ifne;9b b iflt;9c b ifge;9d b ifgt;9e b ifle;9f b if_icmpeq;a0 b if_icmpne;a1 b if_icmplt;a2 b if_icmpge;a3 b if_icmpgt;a4 b if_icmple;a5 b if_acmpeq;a6 b if_acmpne;a7 b goto;a8 b jsr;a9 l ret;aa T tableswitch;ab U lookupswitch;ac - ireturn;ad - lreturn;ae - freturn;af - dreturn;b0 - areturn;b1 - return;b2 p:f getstatic;b3 p:f putstatic;b4 p:f getfield;b5 p:f putfield;b6 p:m invokevirtual;b7 p:m invokespecial;b8 p:m invokestatic;b9 I:i invokeinterface;bb p:c new;bc y newarray;bd p:c anewarray;be - arraylength;bf - athrow;c0 p:c checkcast;c1 p:c instanceof;c2 - monitorenter;c3 - monitorexit;c4 W wide;c5 M:c multianewarray;c6 b ifnull;c7 b ifnonnull;c8 c goto_w;c9 c jsr_w;".charAt(i3)) {
                        case C0327R.styleable.AppCompatTheme_textAppearanceSearchResultSubtitle /* 68 */:
                            i |= 256;
                            break;
                        case C0327R.styleable.AppCompatTheme_searchViewStyle /* 70 */:
                            i |= 64;
                            break;
                        case C0327R.styleable.AppCompatTheme_listPreferredItemHeightLarge /* 73 */:
                            i |= 32;
                            break;
                        case C0327R.styleable.AppCompatTheme_listPreferredItemPaddingLeft /* 74 */:
                            i |= 128;
                            break;
                        case C0327R.styleable.AppCompatTheme_textColorAlertDialogListItem /* 99 */:
                            i |= 512;
                            break;
                        case C0327R.styleable.AppCompatTheme_buttonBarNeutralButtonStyle /* 102 */:
                            i |= 2048;
                            break;
                        case C0327R.styleable.AppCompatTheme_buttonStyleSmall /* 105 */:
                            i |= 8192;
                            break;
                        case 'm':
                            i |= 4096;
                            break;
                        case C0327R.styleable.AppCompatTheme_switchStyle /* 115 */:
                            i |= 1024;
                            break;
                        default:
                            i3++;
                            continue;
                    }
                    i3++;
                }
            }
            int iIndexOf = "00 - nop;01 - aconst_null;02 - iconst_m1;03 - iconst_0;04 - iconst_1;05 - iconst_2;06 - iconst_3;07 - iconst_4;08 - iconst_5;09 - lconst_0;0a - lconst_1;0b - fconst_0;0c - fconst_1;0d - fconst_2;0e - dconst_0;0f - dconst_1;10 y bipush;11 S sipush;12 L:IFcs ldc;13 p:IFcs ldc_w;14 p:DJ ldc2_w;15 l iload;16 m lload;17 l fload;18 m dload;19 l aload;1a 0 iload_0;1b 1 iload_1;1c 2 iload_2;1d 3 iload_3;1e 1 lload_0;1f 2 lload_1;20 3 lload_2;21 4 lload_3;22 0 fload_0;23 1 fload_1;24 2 fload_2;25 3 fload_3;26 1 dload_0;27 2 dload_1;28 3 dload_2;29 4 dload_3;2a 0 aload_0;2b 1 aload_1;2c 2 aload_2;2d 3 aload_3;2e - iaload;2f - laload;30 - faload;31 - daload;32 - aaload;33 - baload;34 - caload;35 - saload;36 - istore;37 - lstore;38 - fstore;39 - dstore;3a - astore;3b 0 istore_0;3c 1 istore_1;3d 2 istore_2;3e 3 istore_3;3f 1 lstore_0;40 2 lstore_1;41 3 lstore_2;42 4 lstore_3;43 0 fstore_0;44 1 fstore_1;45 2 fstore_2;46 3 fstore_3;47 1 dstore_0;48 2 dstore_1;49 3 dstore_2;4a 4 dstore_3;4b 0 astore_0;4c 1 astore_1;4d 2 astore_2;4e 3 astore_3;4f - iastore;50 - lastore;51 - fastore;52 - dastore;53 - aastore;54 - bastore;55 - castore;56 - sastore;57 - pop;58 - pop2;59 - dup;5a - dup_x1;5b - dup_x2;5c - dup2;5d - dup2_x1;5e - dup2_x2;5f - swap;60 - iadd;61 - ladd;62 - fadd;63 - dadd;64 - isub;65 - lsub;66 - fsub;67 - dsub;68 - imul;69 - lmul;6a - fmul;6b - dmul;6c - idiv;6d - ldiv;6e - fdiv;6f - ddiv;70 - irem;71 - lrem;72 - frem;73 - drem;74 - ineg;75 - lneg;76 - fneg;77 - dneg;78 - ishl;79 - lshl;7a - ishr;7b - lshr;7c - iushr;7d - lushr;7e - iand;7f - land;80 - ior;81 - lor;82 - ixor;83 - lxor;84 l iinc;85 - i2l;86 - i2f;87 - i2d;88 - l2i;89 - l2f;8a - l2d;8b - f2i;8c - f2l;8d - f2d;8e - d2i;8f - d2l;90 - d2f;91 - i2b;92 - i2c;93 - i2s;94 - lcmp;95 - fcmpl;96 - fcmpg;97 - dcmpl;98 - dcmpg;99 b ifeq;9a b ifne;9b b iflt;9c b ifge;9d b ifgt;9e b ifle;9f b if_icmpeq;a0 b if_icmpne;a1 b if_icmplt;a2 b if_icmpge;a3 b if_icmpgt;a4 b if_icmple;a5 b if_acmpeq;a6 b if_acmpne;a7 b goto;a8 b jsr;a9 l ret;aa T tableswitch;ab U lookupswitch;ac - ireturn;ad - lreturn;ae - freturn;af - dreturn;b0 - areturn;b1 - return;b2 p:f getstatic;b3 p:f putstatic;b4 p:f getfield;b5 p:f putfield;b6 p:m invokevirtual;b7 p:m invokespecial;b8 p:m invokestatic;b9 I:i invokeinterface;bb p:c new;bc y newarray;bd p:c anewarray;be - arraylength;bf - athrow;c0 p:c checkcast;c1 p:c instanceof;c2 - monitorenter;c3 - monitorexit;c4 W wide;c5 M:c multianewarray;c6 b ifnull;c7 b ifnonnull;c8 c goto_w;c9 c jsr_w;".indexOf(59, i3);
            f882a[iDigit] = i;
            f883b[iDigit] = "00 - nop;01 - aconst_null;02 - iconst_m1;03 - iconst_0;04 - iconst_1;05 - iconst_2;06 - iconst_3;07 - iconst_4;08 - iconst_5;09 - lconst_0;0a - lconst_1;0b - fconst_0;0c - fconst_1;0d - fconst_2;0e - dconst_0;0f - dconst_1;10 y bipush;11 S sipush;12 L:IFcs ldc;13 p:IFcs ldc_w;14 p:DJ ldc2_w;15 l iload;16 m lload;17 l fload;18 m dload;19 l aload;1a 0 iload_0;1b 1 iload_1;1c 2 iload_2;1d 3 iload_3;1e 1 lload_0;1f 2 lload_1;20 3 lload_2;21 4 lload_3;22 0 fload_0;23 1 fload_1;24 2 fload_2;25 3 fload_3;26 1 dload_0;27 2 dload_1;28 3 dload_2;29 4 dload_3;2a 0 aload_0;2b 1 aload_1;2c 2 aload_2;2d 3 aload_3;2e - iaload;2f - laload;30 - faload;31 - daload;32 - aaload;33 - baload;34 - caload;35 - saload;36 - istore;37 - lstore;38 - fstore;39 - dstore;3a - astore;3b 0 istore_0;3c 1 istore_1;3d 2 istore_2;3e 3 istore_3;3f 1 lstore_0;40 2 lstore_1;41 3 lstore_2;42 4 lstore_3;43 0 fstore_0;44 1 fstore_1;45 2 fstore_2;46 3 fstore_3;47 1 dstore_0;48 2 dstore_1;49 3 dstore_2;4a 4 dstore_3;4b 0 astore_0;4c 1 astore_1;4d 2 astore_2;4e 3 astore_3;4f - iastore;50 - lastore;51 - fastore;52 - dastore;53 - aastore;54 - bastore;55 - castore;56 - sastore;57 - pop;58 - pop2;59 - dup;5a - dup_x1;5b - dup_x2;5c - dup2;5d - dup2_x1;5e - dup2_x2;5f - swap;60 - iadd;61 - ladd;62 - fadd;63 - dadd;64 - isub;65 - lsub;66 - fsub;67 - dsub;68 - imul;69 - lmul;6a - fmul;6b - dmul;6c - idiv;6d - ldiv;6e - fdiv;6f - ddiv;70 - irem;71 - lrem;72 - frem;73 - drem;74 - ineg;75 - lneg;76 - fneg;77 - dneg;78 - ishl;79 - lshl;7a - ishr;7b - lshr;7c - iushr;7d - lushr;7e - iand;7f - land;80 - ior;81 - lor;82 - ixor;83 - lxor;84 l iinc;85 - i2l;86 - i2f;87 - i2d;88 - l2i;89 - l2f;8a - l2d;8b - f2i;8c - f2l;8d - f2d;8e - d2i;8f - d2l;90 - d2f;91 - i2b;92 - i2c;93 - i2s;94 - lcmp;95 - fcmpl;96 - fcmpg;97 - dcmpl;98 - dcmpg;99 b ifeq;9a b ifne;9b b iflt;9c b ifge;9d b ifgt;9e b ifle;9f b if_icmpeq;a0 b if_icmpne;a1 b if_icmplt;a2 b if_icmpge;a3 b if_icmpgt;a4 b if_icmple;a5 b if_acmpeq;a6 b if_acmpne;a7 b goto;a8 b jsr;a9 l ret;aa T tableswitch;ab U lookupswitch;ac - ireturn;ad - lreturn;ae - freturn;af - dreturn;b0 - areturn;b1 - return;b2 p:f getstatic;b3 p:f putstatic;b4 p:f getfield;b5 p:f putfield;b6 p:m invokevirtual;b7 p:m invokespecial;b8 p:m invokestatic;b9 I:i invokeinterface;bb p:c new;bc y newarray;bd p:c anewarray;be - arraylength;bf - athrow;c0 p:c checkcast;c1 p:c instanceof;c2 - monitorenter;c3 - monitorexit;c4 W wide;c5 M:c multianewarray;c6 b ifnull;c7 b ifnonnull;c8 c goto_w;c9 c jsr_w;".substring(i3, iIndexOf);
            i2 = iIndexOf + 1;
        }
    }

    /* JADX INFO: renamed from: a */
    public static String m837a(int i) {
        String str = f883b[i];
        if (str != null) {
            return str;
        }
        String str2 = "unused_" + C1067a.m2560x(i);
        f883b[i] = str2;
        return str2;
    }

    /* JADX INFO: renamed from: b */
    public static int m838b(int i) {
        return f882a[i];
    }
}
